LICENSE
README.md
setup.py
rlp/__init__.py
rlp/converters.py
rlp/rlp.py
simple_rlp.egg-info/PKG-INFO
simple_rlp.egg-info/SOURCES.txt
simple_rlp.egg-info/dependency_links.txt
simple_rlp.egg-info/top_level.txt