Metadata-Version: 2.1
Name: simple-rlp
Version: 0.1.3
Summary: RLP (Recursive Length Prefix) - Encode and decode data structures
Home-page: https://github.com/SamuelHaidu/simple-rlp
Author: Samuel Haidu
Author-email: samuelhaidu3@gmail.com
License: MIT Custom
Classifier: License :: OSI Approved :: MIT License
Classifier: Programming Language :: Python :: 3
Requires-Python: >=3.6
License-File: LICENSE
